eegemolib/__init__.py
eegemolib/cfg/.gitkeep
eegemolib/cfg/default.yaml
eegemolib/cfg/datasets/CAS.yaml
eegemolib/cfg/datasets/DEAP.yaml
eegemolib/cfg/datasets/DREAMER.yaml
eegemolib/cfg/datasets/HCI_bak.yaml
eegemolib/cfg/datasets/MAHNOB_HCI.yaml
eegemolib/cfg/datasets/MPED.yaml
eegemolib/cfg/datasets/SEED.yaml
eegemolib/cfg/datasets/SEEDIV.yaml
eegemolib/cfg/datasets/SEEDV.yaml
eegemolib/cfg/datasets/SEED_extracted_features.yaml
eegemolib/cfg/datasets/SEED_preprocessed_EEG.yaml
eegemolib/cfg/models/README.md
eegemolib/cfg/models/2d/DBNNet.yaml
eegemolib/cfg/models/2d/EEGNet.yaml
eegemolib/cfg/models/2d/FCBNet.yaml
eegemolib/cfg/models/2d/TSception.yaml
eegemolib/cfg/models/3d/CCNN.yaml
eegemolib/cfg/models/3d/CRNN.yaml
eegemolib/data/CAS_dataset.py
eegemolib/data/MPED_dataset.py
eegemolib/data/__init__.py
eegemolib/data/base_dataset.py
eegemolib/data/deap_dataset.py
eegemolib/data/dreamer_dataset.py
eegemolib/data/hci_dataset.py
eegemolib/data/seed_dataset.py
eegemolib/data/seediv_dataset.py
eegemolib/data/seedv_dataset.py
eegemolib/engine/.gitkeep
eegemolib/engine/EEGEmo.py
eegemolib/engine/__init__.py
eegemolib/features/__init__.py
eegemolib/features/extraction/__init__.py
eegemolib/features/extraction/featureExtraction.py
eegemolib/features/selection/__init__.py
eegemolib/features/selection/featureSelection.py
eegemolib/models/__init__.py
eegemolib/models/base_model.py
eegemolib/models/1d_analysis/1d_analysis.py
eegemolib/models/1d_analysis/__init__.py
eegemolib/models/2d_analysis/2d_analysis.py
eegemolib/models/2d_analysis/DBNNet.py
eegemolib/models/2d_analysis/DGCNN.py
eegemolib/models/2d_analysis/DeepConvNet.py
eegemolib/models/2d_analysis/EEGNet.py
eegemolib/models/2d_analysis/FCBNet.py
eegemolib/models/2d_analysis/LSTM.py
eegemolib/models/2d_analysis/ShallowConvNet.py
eegemolib/models/2d_analysis/TSception.py
eegemolib/models/2d_analysis/__init__.py
eegemolib/models/2d_analysis/layers.py
eegemolib/models/2d_analysis/sru/__init__.py
eegemolib-0.0.1.dist-info/METADATA
eegemolib-0.0.1.dist-info/WHEEL
eegemolib-0.0.1.dist-info/licenses/LICENSE
eegemolib-0.0.1.dist-info/RECORD
